Workbook

Sheet Summary
A1: DemoBlaze — Test Case Suite (Login, Cart, Place Order)
A3: Application | B3: https://www.demoblaze.com
A4: Scope | B4: Login (incl. sign-up / logout), Cart, Place Order; supporting API, contract, concurrency & performance checks; payment-gateway test strategy
A5: Automation repo | B5: Specs referenced in column 'Automated In' (Playwright + TypeScript)
A6: Test IDs | B6: TC IDs appear in automated test titles, e.g. [TC-ORDER-001], for traceability
A7: Automation legend | B7: Automated = in the suite · Candidate = good next automation target · Manual = exploratory / not cost-effective to automate
A8: Known-bug tests | B8: Tagged @known-bug and marked test.fail(): they pass while the defect exists and alert the team when it is fixed
A9: How to use | B9: Fill 'Status' (dropdown) and 'Actual Result / Notes' during execution; this summary updates automatically
A10: Payment gateway | B10: The “Test Strategy – Payment Gateway” sheet maps the same techniques to a high-traffic payment system: idempotency, concurrency, Redis, message queue, database, AWS, API integration, security, performance (proposed, not run against DemoBlaze)
A12: Module | B12: Total | C12: P1 | D12: P2 | E12: P3 | F12: Functional | G12: Negative | H12: Edge | I12: Other types | J12: Automated | K12: Candidate | L12: Manual | M12: Automation % | N12: Pass | O12: Fail | P12: Not Run
A13: Login | B13: =COUNTA(Login!$A$2:$A$26) | C13: =COUNTIF(Login!$E$2:$E$26,"P1") | D13: =COUNTIF(Login!$E$2:$E$26,"P2") | E13: =COUNTIF(Login!$E$2:$E$26,"P3") | F13: =COUNTIF(Login!$D$2:$D$26,"Functional") | G13: =COUNTIF(Login!$D$2:$D$26,"Negative") | H13: =COUNTIF(Login!$D$2:$D$26,"Edge") | I13: =B13-F13-G13-H13 | J13: =COUNTIF(Login!$J$2:$J$26,"Automated") | K13: =COUNTIF(Login!$J$2:$J$26,"Candidate") | L13: =COUNTIF(Login!$J$2:$J$26,"Manual") | M13: =IF(B13=0,0,J13/B13) | N13: =COUNTIF(Login!$M$2:$M$26,"Pass") | O13: =COUNTIF(Login!$M$2:$M$26,"Fail") | P13: =COUNTIF(Login!$M$2:$M$26,"Not Run")
A14: Cart | B14: =COUNTA(Cart!$A$2:$A$22) | C14: =COUNTIF(Cart!$E$2:$E$22,"P1") | D14: =COUNTIF(Cart!$E$2:$E$22,"P2") | E14: =COUNTIF(Cart!$E$2:$E$22,"P3") | F14: =COUNTIF(Cart!$D$2:$D$22,"Functional") | G14: =COUNTIF(Cart!$D$2:$D$22,"Negative") | H14: =COUNTIF(Cart!$D$2:$D$22,"Edge") | I14: =B14-F14-G14-H14 | J14: =COUNTIF(Cart!$J$2:$J$22,"Automated") | K14: =COUNTIF(Cart!$J$2:$J$22,"Candidate") | L14: =COUNTIF(Cart!$J$2:$J$22,"Manual") | M14: =IF(B14=0,0,J14/B14) | N14: =COUNTIF(Cart!$M$2:$M$22,"Pass") | O14: =COUNTIF(Cart!$M$2:$M$22,"Fail") | P14: =COUNTIF(Cart!$M$2:$M$22,"Not Run")
A15: Place Order | B15: =COUNTA('Place Order'!$A$2:$A$18) | C15: =COUNTIF('Place Order'!$E$2:$E$18,"P1") | D15: =COUNTIF('Place Order'!$E$2:$E$18,"P2") | E15: =COUNTIF('Place Order'!$E$2:$E$18,"P3") | F15: =COUNTIF('Place Order'!$D$2:$D$18,"Functional") | G15: =COUNTIF('Place Order'!$D$2:$D$18,"Negative") | H15: =COUNTIF('Place Order'!$D$2:$D$18,"Edge") | I15: =B15-F15-G15-H15 | J15: =COUNTIF('Place Order'!$J$2:$J$18,"Automated") | K15: =COUNTIF('Place Order'!$J$2:$J$18,"Candidate") | L15: =COUNTIF('Place Order'!$J$2:$J$18,"Manual") | M15: =IF(B15=0,0,J15/B15) | N15: =COUNTIF('Place Order'!$M$2:$M$18,"Pass") | O15: =COUNTIF('Place Order'!$M$2:$M$18,"Fail") | P15: =COUNTIF('Place Order'!$M$2:$M$18,"Not Run")
A16: API & Performance | B16: =COUNTA('API & Performance'!$A$2:$A$14) | C16: =COUNTIF('API & Performance'!$E$2:$E$14,"P1") | D16: =COUNTIF('API & Performance'!$E$2:$E$14,"P2") | E16: =COUNTIF('API & Performance'!$E$2:$E$14,"P3") | F16: =COUNTIF('API & Performance'!$D$2:$D$14,"Functional") | G16: =COUNTIF('API & Performance'!$D$2:$D$14,"Negative") | H16: =COUNTIF('API & Performance'!$D$2:$D$14,"Edge") | I16: =B16-F16-G16-H16 | J16: =COUNTIF('API & Performance'!$J$2:$J$14,"Automated") | K16: =COUNTIF('API & Performance'!$J$2:$J$14,"Candidate") | L16: =COUNTIF('API & Performance'!$J$2:$J$14,"Manual") | M16: =IF(B16=0,0,J16/B16) | N16: =COUNTIF('API & Performance'!$M$2:$M$14,"Pass") | O16: =COUNTIF('API & Performance'!$M$2:$M$14,"Fail") | P16: =COUNTIF('API & Performance'!$M$2:$M$14,"Not Run")
A17: Concurrency & Contract | B17: =COUNTA('Concurrency & Contract'!$A$2:$A$19) | C17: =COUNTIF('Concurrency & Contract'!$E$2:$E$19,"P1") | D17: =COUNTIF('Concurrency & Contract'!$E$2:$E$19,"P2") | E17: =COUNTIF('Concurrency & Contract'!$E$2:$E$19,"P3") | F17: =COUNTIF('Concurrency & Contract'!$D$2:$D$19,"Functional") | G17: =COUNTIF('Concurrency & Contract'!$D$2:$D$19,"Negative") | H17: =COUNTIF('Concurrency & Contract'!$D$2:$D$19,"Edge") | I17: =B17-F17-G17-H17 | J17: =COUNTIF('Concurrency & Contract'!$J$2:$J$19,"Automated") | K17: =COUNTIF('Concurrency & Contract'!$J$2:$J$19,"Candidate") | L17: =COUNTIF('Concurrency & Contract'!$J$2:$J$19,"Manual") | M17: =IF(B17=0,0,J17/B17) | N17: =COUNTIF('Concurrency & Contract'!$M$2:$M$19,"Pass") | O17: =COUNTIF('Concurrency & Contract'!$M$2:$M$19,"Fail") | P17: =COUNTIF('Concurrency & Contract'!$M$2:$M$19,"Not Run")
A18: TOTAL | B18: =SUM(B13:B17) | C18: =SUM(C13:C17) | D18: =SUM(D13:D17) | E18: =SUM(E13:E17) | F18: =SUM(F13:F17) | G18: =SUM(G13:G17) | H18: =SUM(H13:H17) | I18: =SUM(I13:I17) | ... L18: =SUM(L13:L17) | M18: =IF(B18=0,0,J18/B18) | N18: =SUM(N13:N17) | O18: =SUM(O13:O17) | P18: =SUM(P13:P17)
A21: Payment gateway strategy | B21: Cases | C21: P1 | D21: P2 | E21: P3 | F21: With DemoBlaze analogue
A22: Payment & idempotency | B22: =COUNTIF('Test Strategy – Payment Gateway'!$B$2:$B$63,$A22) | C22: =COUNTIFS('Test Strategy – Payment Gateway'!$B$2:$B$63,$A22,'Test Strategy – Payment Gateway'!$F$2:$F$63,"P1") | D22: =COUNTIFS('Test Strategy – Payment Gateway'!$B$2:$B$63,$A22,'Test Strategy – Payment Gateway'!$F$2:$F$63,"P2") | E22: =COUNTIFS('Test Strategy – Payment Gateway'!$B$2:$B$63,$A22,'Test Strategy – Payment Gateway'!$F$2:$F$63,"P3") | F22: =COUNTIFS('Test Strategy – Payment Gateway'!$B$2:$B$63,$A22,'Test Strategy – Payment Gateway'!$L$2:$L$63,"<>—")
A23: Concurrency | B23: =COUNTIF('Test Strategy – Payment Gateway'!$B$2:$B$63,$A23) | C23: =COUNTIFS('Test Strategy – Payment Gateway'!$B$2:$B$63,$A23,'Test Strategy – Payment Gateway'!$F$2:$F$63,"P1") | D23: =COUNTIFS('Test Strategy – Payment Gateway'!$B$2:$B$63,$A23,'Test Strategy – Payment Gateway'!$F$2:$F$63,"P2") | E23: =COUNTIFS('Test Strategy – Payment Gateway'!$B$2:$B$63,$A23,'Test Strategy – Payment Gateway'!$F$2:$F$63,"P3") | F23: =COUNTIFS('Test Strategy – Payment Gateway'!$B$2:$B$63,$A23,'Test Strategy – Payment Gateway'!$L$2:$L$63,"<>—")
A24: Redis | B24: =COUNTIF('Test Strategy – Payment Gateway'!$B$2:$B$63,$A24) | C24: =COUNTIFS('Test Strategy – Payment Gateway'!$B$2:$B$63,$A24,'Test Strategy – Payment Gateway'!$F$2:$F$63,"P1") | D24: =COUNTIFS('Test Strategy – Payment Gateway'!$B$2:$B$63,$A24,'Test Strategy – Payment Gateway'!$F$2:$F$63,"P2") | E24: =COUNTIFS('Test Strategy – Payment Gateway'!$B$2:$B$63,$A24,'Test Strategy – Payment Gateway'!$F$2:$F$63,"P3") | F24: =COUNTIFS('Test Strategy – Payment Gateway'!$B$2:$B$63,$A24,'Test Strategy – Payment Gateway'!$L$2:$L$63,"<>—")
A25: Message queue | B25: =COUNTIF('Test Strategy – Payment Gateway'!$B$2:$B$63,$A25) | C25: =COUNTIFS('Test Strategy – Payment Gateway'!$B$2:$B$63,$A25,'Test Strategy – Payment Gateway'!$F$2:$F$63,"P1") | D25: =COUNTIFS('Test Strategy – Payment Gateway'!$B$2:$B$63,$A25,'Test Strategy – Payment Gateway'!$F$2:$F$63,"P2") | E25: =COUNTIFS('Test Strategy – Payment Gateway'!$B$2:$B$63,$A25,'Test Strategy – Payment Gateway'!$F$2:$F$63,"P3") | F25: =COUNTIFS('Test Strategy – Payment Gateway'!$B$2:$B$63,$A25,'Test Strategy – Payment Gateway'!$L$2:$L$63,"<>—")
A26: Database | B26: =COUNTIF('Test Strategy – Payment Gateway'!$B$2:$B$63,$A26) | C26: =COUNTIFS('Test Strategy – Payment Gateway'!$B$2:$B$63,$A26,'Test Strategy – Payment Gateway'!$F$2:$F$63,"P1") | D26: =COUNTIFS('Test Strategy – Payment Gateway'!$B$2:$B$63,$A26,'Test Strategy – Payment Gateway'!$F$2:$F$63,"P2") | E26: =COUNTIFS('Test Strategy – Payment Gateway'!$B$2:$B$63,$A26,'Test Strategy – Payment Gateway'!$F$2:$F$63,"P3") | F26: =COUNTIFS('Test Strategy – Payment Gateway'!$B$2:$B$63,$A26,'Test Strategy – Payment Gateway'!$L$2:$L$63,"<>—")
A27: AWS | B27: =COUNTIF('Test Strategy – Payment Gateway'!$B$2:$B$63,$A27) | C27: =COUNTIFS('Test Strategy – Payment Gateway'!$B$2:$B$63,$A27,'Test Strategy – Payment Gateway'!$F$2:$F$63,"P1") | D27: =COUNTIFS('Test Strategy – Payment Gateway'!$B$2:$B$63,$A27,'Test Strategy – Payment Gateway'!$F$2:$F$63,"P2") | E27: =COUNTIFS('Test Strategy – Payment Gateway'!$B$2:$B$63,$A27,'Test Strategy – Payment Gateway'!$F$2:$F$63,"P3") | F27: =COUNTIFS('Test Strategy – Payment Gateway'!$B$2:$B$63,$A27,'Test Strategy – Payment Gateway'!$L$2:$L$63,"<>—")
A28: API integration | B28: =COUNTIF('Test Strategy – Payment Gateway'!$B$2:$B$63,$A28) | C28: =COUNTIFS('Test Strategy – Payment Gateway'!$B$2:$B$63,$A28,'Test Strategy – Payment Gateway'!$F$2:$F$63,"P1") | D28: =COUNTIFS('Test Strategy – Payment Gateway'!$B$2:$B$63,$A28,'Test Strategy – Payment Gateway'!$F$2:$F$63,"P2") | E28: =COUNTIFS('Test Strategy – Payment Gateway'!$B$2:$B$63,$A28,'Test Strategy – Payment Gateway'!$F$2:$F$63,"P3") | F28: =COUNTIFS('Test Strategy – Payment Gateway'!$B$2:$B$63,$A28,'Test Strategy – Payment Gateway'!$L$2:$L$63,"<>—")
A29: Security | B29: =COUNTIF('Test Strategy – Payment Gateway'!$B$2:$B$63,$A29) | C29: =COUNTIFS('Test Strategy – Payment Gateway'!$B$2:$B$63,$A29,'Test Strategy – Payment Gateway'!$F$2:$F$63,"P1") | D29: =COUNTIFS('Test Strategy – Payment Gateway'!$B$2:$B$63,$A29,'Test Strategy – Payment Gateway'!$F$2:$F$63,"P2") | E29: =COUNTIFS('Test Strategy – Payment Gateway'!$B$2:$B$63,$A29,'Test Strategy – Payment Gateway'!$F$2:$F$63,"P3") | F29: =COUNTIFS('Test Strategy – Payment Gateway'!$B$2:$B$63,$A29,'Test Strategy – Payment Gateway'!$L$2:$L$63,"<>—")
A30: Performance | B30: =COUNTIF('Test Strategy – Payment Gateway'!$B$2:$B$63,$A30) | C30: =COUNTIFS('Test Strategy – Payment Gateway'!$B$2:$B$63,$A30,'Test Strategy – Payment Gateway'!$F$2:$F$63,"P1") | D30: =COUNTIFS('Test Strategy – Payment Gateway'!$B$2:$B$63,$A30,'Test Strategy – Payment Gateway'!$F$2:$F$63,"P2") | E30: =COUNTIFS('Test Strategy – Payment Gateway'!$B$2:$B$63,$A30,'Test Strategy – Payment Gateway'!$F$2:$F$63,"P3") | F30: =COUNTIFS('Test Strategy – Payment Gateway'!$B$2:$B$63,$A30,'Test Strategy – Payment Gateway'!$L$2:$L$63,"<>—")
A31: TOTAL | B31: =SUM(B22:B30) | C31: =SUM(C22:C30) | D31: =SUM(D22:D30) | E31: =SUM(E22:E30) | F31: =SUM(F22:F30)

Sheet Login
A1: TC ID | B1: Scenario | C1: Title | D1: Type | E1: Priority | F1: Preconditions | G1: Test Data | H1: Steps | I1: Expected Result | J1: Automation | K1: Automated In | L1: Tags | M1: Status | N1: Actual Result / Notes
A2: TC-LOGIN-001 | B2: Valid login | C2: Log in with valid credentials | D2: Functional | E2: P1 | F2: A registered user exists (auto-provisioned via API by the framework) | G2: username / password of the registered user | H2: 1. Open https://www.demoblaze.com 2. Click 'Log in' in the navbar 3. Enter valid username and password 4. Click 'Log in' | I2: Modal closes, page reloads; navbar shows 'Welcome <username>' and 'Log out'; 'Log in' and 'Sign up' are hidden. | J2: Automated | K2: tests/ui/login.spec.ts | L2: @smoke @regression | M2: Not Run
A3: TC-LOGIN-002 | B3: Invalid login | C3: Wrong password is rejected | D3: Negative | E3: P1 | F3: A registered user exists (auto-provisioned via API by the framework) | G3: valid username, wrong password | H3: 1. Open Log in modal 2. Enter valid username and an incorrect password 3. Click 'Log in' | I3: Alert 'Wrong password.' is shown; user stays logged out. | J3: Automated | K3: tests/ui/login.spec.ts | L3: @regression | M3: Not Run
A4: TC-LOGIN-003 | B4: Invalid login | C4: Unregistered username is rejected | D4: Negative | E4: P1 | F4: — | G4: random never-registered username | H4: 1. Open Log in modal 2. Enter an unregistered username and any password 3. Click 'Log in' | I4: Alert 'User does not exist.' is shown; user stays logged out. | J4: Automated | K4: tests/ui/login.spec.ts | L4: @regression | M4: Not Run
A5: TC-LOGIN-004 | B5: Field validation | C5: Both fields empty | D5: Negative | E5: P2 | F5: — | G5: username='' password='' | H5: 1. Open Log in modal 2. Leave both fields empty 3. Click 'Log in' | I5: Alert 'Please fill out Username and Password.'; no login request succeeds. | J5: Automated | K5: tests/ui/login.spec.ts | L5: @regression | M5: Not Run
A6: TC-LOGIN-005 | B6: Field validation | C6: Username empty | D6: Negative | E6: P2 | F6: — | G6: username='' password='anyPassword1' | H6: 1. Open Log in modal 2. Fill only the password 3. Click 'Log in' | I6: Alert 'Please fill out Username and Password.' | J6: Automated | K6: tests/ui/login.spec.ts | L6: @regression | M6: Not Run
A7: TC-LOGIN-006 | B7: Field validation | C7: Password empty | D7: Negative | E7: P2 | F7: — | G7: username='anyUser' password='' | H7: 1. Open Log in modal 2. Fill only the username 3. Click 'Log in' | I7: Alert 'Please fill out Username and Password.' | J7: Automated | K7: tests/ui/login.spec.ts | L7: @regression | M7: Not Run
A8: TC-LOGIN-007 | B8: UI / Security | C8: Password input is masked | D8: UI | E8: P2 | F8: — | G8: — | H8: 1. Open Log in modal 2. Type into the Password field | I8: Password field is type='password'; characters are masked. | J8: Automated | K8: tests/ui/login.spec.ts | L8: @regression | M8: Not Run
A9: TC-LOGIN-008 | B9: Session | C9: Session survives a page reload | D9: Functional | E9: P2 | F9: A registered user exists (auto-provisioned via API by the framework) | G9: — | H9: 1. Log in with valid credentials 2. Reload the page (F5) | I9: User remains logged in ('Welcome <username>' still shown). | J9: Automated | K9: tests/ui/login.spec.ts | L9: @regression | M9: Not Run
A10: TC-LOGIN-009 | B10: Logout | C10: User can log out | D10: Functional | E10: P1 | F10: User is logged in | G10: — | H10: 1. Log in 2. Click 'Log out' | I10: User is redirected to home; 'Log in' / 'Sign up' visible, 'Welcome' and 'Log out' hidden. | J10: Automated | K10: tests/ui/login.spec.ts | L10: @smoke @regression | M10: Not Run
A11: TC-LOGIN-010 | B11: Modal behaviour | C11: Closing the modal does not log the user in | D11: Edge | E11: P3 | F11: A registered user exists (auto-provisioned via API by the framework) | G11: valid credentials | H11: 1. Open Log in modal 2. Fill valid credentials 3. Click 'Close' instead of 'Log in' | I11: Modal closes; user is still logged out. | J11: Automated | K11: tests/ui/login.spec.ts | L11: @regression | M11: Not Run
A12: TC-LOGIN-011 | B12: Security | C12: SQL-injection style input is treated as text | D12: Security | E12: P2 | F12: — | G12: username="' OR '1'='1' --" password="' OR '1'='1" | H12: 1. Open Log in modal 2. Enter the injection payload in both fields 3. Click 'Log in' | I12: Alert 'User does not exist.'; no authentication bypass, no server error. | J12: Automated | K12: tests/ui/login.spec.ts | L12: @regression @security | M12: Not Run
A13: TC-LOGIN-012 | B13: Sign up → Login | C13: A newly signed-up user can log in | D13: Functional | E13: P1 | F13: — | G13: new unique username + password | H13: 1. Click 'Sign up' 2. Register a new unique user 3. Accept 'Sign up successful.' 4. Log in with the new credentials | I13: Sign-up alert 'Sign up successful.'; login succeeds with 'Welcome <username>'. | J13: Automated | K13: tests/ui/login.spec.ts | L13: @regression | M13: Not Run
A14: TC-LOGIN-013 | B14: Sign up | C14: Duplicate username is rejected on sign up | D14: Negative | E14: P2 | F14: A registered user exists (auto-provisioned via API by the framework) | G14: existing username | H14: 1. Click 'Sign up' 2. Enter an already registered username 3. Click 'Sign up' | I14: Alert 'This user already exist.' | J14: Automated | K14: tests/ui/login.spec.ts | L14: @regression | M14: Not Run
A15: TC-LOGIN-014 | B15: Modal behaviour | C15: Close login modal with the × icon / Esc | D15: UI | E15: P3 | F15: — | G15: — | H15: 1. Open Log in modal 2. Click the × icon 3. Re-open and press Esc | I15: Modal closes each time; page remains usable. | J15: Manual | M15: Not Run
A16: TC-LOGIN-015 | B16: Edge input | C16: Username with leading/trailing spaces | D16: Edge | E16: P3 | F16: A registered user exists (auto-provisioned via API by the framework) | G16: ' <username> ' | H16: 1. Open Log in modal 2. Enter the valid username padded with spaces + valid password 3. Click 'Log in' | I16: Behaviour is consistent and defined (either trimmed and accepted, or clearly rejected) — no confusing error. | J16: Candidate | M16: Not Run
A17: TC-LOGIN-016 | B17: Edge input | C17: Username case sensitivity | D17: Edge | E17: P3 | F17: A registered user exists (auto-provisioned via API by the framework) | G17: USERNAME in different case | H17: 1. Open Log in modal 2. Enter the username with changed letter case + valid password 3. Click 'Log in' | I17: Matches product rule for usernames (case-sensitive → 'User does not exist.'). Document actual behaviour. | J17: Candidate | M17: Not Run
A18: TC-LOGIN-017 | B18: Edge input | C18: Very long username / password (500+ chars) | D18: Edge | E18: P3 | F18: — | G18: 500-char strings | H18: 1. Open Log in modal 2. Paste 500+ characters into both fields 3. Click 'Log in' | I18: Handled gracefully: an error alert, no hang, no layout break. | J18: Candidate | M18: Not Run
A19: TC-LOGIN-018 | B19: Edge input | C19: Unicode credentials | D19: Edge | E19: P3 | F19: User registered with unicode username e.g. 'người_dùng' | G19: unicode username / password | H19: 1. Sign up with a unicode username 2. Log in with it | I19: Login succeeds; welcome text renders unicode correctly. | J19: Candidate | M19: Not Run
A20: TC-LOGIN-019 | B20: Security | C20: Script injection in username is not executed | D20: Security | E20: P2 | F20: — | G20: <script>alert(1)</script> | H20: 1. Sign up with the payload as username (if accepted) 2. Log in with it 3. Observe navbar | I20: No script executes; payload is rendered as plain text in 'Welcome …'. | J20: Candidate | M20: Not Run
A21: TC-LOGIN-020 | B21: Usability | C21: Submit with Enter key | D21: Usability | E21: P3 | F21: A registered user exists (auto-provisioned via API by the framework) | G21: valid credentials | H21: 1. Open Log in modal 2. Fill credentials 3. Press Enter in the password field | I21: Form submits (or behaviour documented if not supported). | J21: Manual | M21: Not Run
A22: TC-LOGIN-021 | B22: Robustness | C22: Double-click on 'Log in' | D22: Edge | E22: P3 | F22: A registered user exists (auto-provisioned via API by the framework) | G22: valid credentials | H22: 1. Open Log in modal 2. Fill credentials 3. Double-click 'Log in' quickly | I22: Single successful login; no duplicate errors. | J22: Manual | M22: Not Run
A23: TC-LOGIN-022 | B23: Session | C23: Login state shared between tabs | D23: Functional | E23: P3 | F23: A registered user exists (auto-provisioned via API by the framework) | G23: — | H23: 1. Log in in tab A 2. Open the site in tab B | I23: Tab B shows the user as logged in (cookie-based session). | J23: Manual | M23: Not Run
A24: TC-LOGIN-023 | B24: Security | C24: Repeated wrong passwords (brute force) | D24: Security | E24: P2 | F24: A registered user exists (auto-provisioned via API by the framework) | G24: 10 wrong passwords in a row | H24: 1. Attempt login 10× with wrong password | I24: Account lockout / throttling / CAPTCHA after N failures (security expectation). Record actual behaviour. | J24: Manual | M24: Not Run
A25: TC-LOGIN-024 | B25: Session | C25: Expired / tampered token | D25: Negative | E25: P3 | F25: User logged in | G25: edit 'tokenp_' cookie to a random value | H25: 1. Log in 2. Change the 'tokenp_' cookie value in DevTools 3. Reload the page | I25: User treated as logged out or alert 'Bad parameter, token malformed.' / 'Your token has expired, please login again.' | J25: Manual | M25: Not Run
A26: TC-LOGIN-025 | B26: Compatibility | C26: Login works on Chrome, Firefox, Safari and mobile | D26: Compatibility | E26: P2 | F26: A registered user exists (auto-provisioned via API by the framework) | G26: — | H26: 1. Run TC-LOGIN-001 and TC-LOGIN-009 on each browser / device | I26: Same behaviour on all targets (hamburger menu used on mobile). | J26: Automated | K26: playwright.config.ts (projects) | L26: @smoke (mobile) | M26: Not Run

Sheet Cart
A1: TC ID | B1: Scenario | C1: Title | D1: Type | E1: Priority | F1: Preconditions | G1: Test Data | H1: Steps | I1: Expected Result | J1: Automation | K1: Automated In | L1: Tags | M1: Status | N1: Actual Result / Notes
A2: TC-CART-001 | B2: Add to cart | C2: Guest adds a product from the catalogue | D2: Functional | E2: P1 | F2: Guest (not logged in) | G2: Samsung galaxy s6 | H2: 1. Open home page 2. Click the product 3. Note the price 4. Click 'Add to cart' 5. Accept the alert 6. Open Cart | I2: Alert 'Product added' shown; cart has exactly 1 line with the same title and price; Total equals that price. | J2: Automated | K2: tests/ui/cart.spec.ts | L2: @smoke @regression | M2: Not Run
A3: TC-CART-002 | B3: Empty cart | C3: Empty cart shows no lines and no total | D3: Edge | E3: P2 | F3: New guest session | G3: — | H3: 1. Open cart.html in a fresh session | I3: No product rows; Total is empty; 'Place Order' button visible. | J3: Automated | K3: tests/ui/cart.spec.ts | L3: @regression | M3: Not Run
A4: TC-CART-003 | B4: Isolation | C4: Cart of one guest is not visible to another guest | D4: Functional | E4: P2 | F4: Two separate browser sessions | G4: Nexus 6 | H4: 1. Session A: add a product 2. Session B (new browser context): open Cart | I4: Session B cart is empty. | J4: Automated | K4: tests/ui/cart.spec.ts | L4: @regression | M4: Not Run
A5: TC-CART-004 | B5: Add to cart | C5: Logged-in user adds a product | D5: Functional | E5: P1 | F5: User is logged in | G5: Nokia lumia 1520 | H5: 1. Log in 2. Open product page 3. Click 'Add to cart' 4. Open Cart | I5: Alert 'Product added.'; cart shows the product with correct title and price. | J5: Automated | K5: tests/ui/cart.spec.ts | L5: @smoke @regression | M5: Not Run
A6: TC-CART-005 | B6: Total | C6: Total equals the sum of several different products | D6: Functional | E6: P1 | F6: User logged in, empty cart | G6: Samsung galaxy s6, Sony vaio i5, Apple monitor 24 (phone, laptop, monitor) | H6: 1. Add the three products 2. Open Cart | I6: 3 lines with the correct titles; Total = sum of the three product-page prices. | J6: Automated | K6: tests/ui/cart.spec.ts | L6: @regression | M6: Not Run
A7: TC-CART-006 | B7: Quantity | C7: Adding the same product twice | D7: Edge | E7: P2 | F7: User logged in, empty cart | G7: Nexus 6 ×2 | H7: 1. Add Nexus 6 2. Add Nexus 6 again 3. Open Cart | I7: Two separate lines (no quantity column); Total = 2 × price. | J7: Automated | K7: tests/ui/cart.spec.ts | L7: @regression | M7: Not Run
A8: TC-CART-007 | B8: Delete | C8: Deleting a line updates the cart and total | D8: Functional | E8: P1 | F8: Cart has Samsung galaxy s6 + Apple monitor 24 | G8: — | H8: 1. Open Cart 2. Click 'Delete' on Samsung galaxy s6 | I8: Line removed after reload; only Apple monitor 24 remains; Total = its price. | J8: Automated | K8: tests/ui/cart.spec.ts | L8: @regression | M8: Not Run
A9: TC-CART-008 | B9: Delete | C9: Deleting the last line leaves an empty cart | D9: Edge | E9: P2 | F9: Cart has 1 item | G9: — | H9: 1. Open Cart 2. Delete the only line | I9: Cart empty; Total empty. | J9: Automated | K9: tests/ui/cart.spec.ts | L9: @regression | M9: Not Run
A10: TC-CART-009 | B10: Persistence | C10: Cart persists across logout and login | D10: Functional | E10: P1 | F10: User logged in, empty cart | G10: Sony vaio i5 | H10: 1. Add a product 2. Log out 3. Log in again 4. Open Cart | I10: The product is still in the cart (server-side cart). | J10: Automated | K10: tests/ui/cart.spec.ts | L10: @regression | M10: Not Run
A11: TC-CART-010 | B11: Integration | C11: Items added via API are rendered in the UI cart | D11: Functional | E11: P2 | F11: User logged in | G11: 2 products added via POST /addtocart | H11: 1. Add products through the API 2. Open Cart in the UI | I11: UI shows both lines; Total = sum of their API prices. | J11: Automated | K11: tests/ui/cart.spec.ts | L11: @regression @hybrid | M11: Not Run
A12: TC-CART-011 | B12: UI | C12: Cart line layout | D12: UI | E12: P3 | F12: Cart has items | G12: — | H12: 1. Open Cart 2. Inspect each row | I12: Each row shows Pic, Title, Price and a 'Delete' link; headers Pic/Title/Price/x. | J12: Manual | M12: Not Run
A13: TC-CART-012 | B13: Robustness | C13: Double-click 'Add to cart' | D13: Edge | E13: P2 | F13: — | G13: any product | H13: 1. Open product page 2. Double-click 'Add to cart' quickly 3. Open Cart | I13: Behaviour is defined: either 1 or 2 lines, matching the number of 'Product added' alerts. | J13: Candidate | M13: Not Run
A14: TC-CART-013 | B14: Navigation | C14: Open cart via direct URL | D14: Functional | E14: P3 | F14: Cart has items | G14: /cart.html | H14: 1. Type https://www.demoblaze.com/cart.html in the address bar | I14: Cart loads with all lines and correct total. | J14: Manual | M14: Not Run
A15: TC-CART-014 | B15: Negative | C15: Invalid product id | D15: Negative | E15: P3 | F15: — | G15: prod.html?idp_=99999 | H15: 1. Open prod.html?idp_=99999 2. Click 'Add to cart' if shown 3. Open Cart | I15: Graceful 'not found' handling; no empty/undefined line added to the cart. | J15: Candidate | M15: Not Run
A16: TC-CART-015 | B16: Negative | C16: Network failure while adding | D16: Negative | E16: P3 | F16: — | G16: DevTools → Offline | H16: 1. Open product page 2. Go offline 3. Click 'Add to cart' | I16: User is informed the item was not added; no false 'Product added' alert. | J16: Manual | M16: Not Run
A17: TC-CART-016 | B17: Guest → login | C17: Guest cart after logging in | D17: Edge | E17: P3 | F17: Guest has items in cart | G17: — | H17: 1. As guest add an item 2. Log in 3. Open Cart | I17: Defined behaviour (merge or keep separate) — document actual result. | J17: Manual | M17: Not Run
A18: TC-CART-017 | B18: Volume | C18: Large cart (20+ lines) | D18: Edge | E18: P3 | F18: User logged in | G18: 20 products | H18: 1. Add 20 items (API seeding) 2. Open Cart | I18: All lines render; Total correct; page loads within performance budget. | J18: Candidate | M18: Not Run
A19: TC-CART-018 | B19: Delete | C19: Deleting one of two identical lines | D19: Edge | E19: P3 | F19: Cart has Nexus 6 ×2 | G19: — | H19: 1. Open Cart 2. Delete one Nexus 6 line | I19: Exactly one Nexus 6 line remains. | J19: Candidate | M19: Not Run
A20: TC-CART-019 | B20: Consistency | C20: Cart in two tabs | D20: Edge | E20: P3 | F20: User logged in | G20: — | H20: 1. Open Cart in tabs A and B 2. Delete an item in A 3. Reload B | I20: B reflects the deletion after reload. | J20: Manual | M20: Not Run
A21: TC-CART-020 | B21: Guest session | C21: Guest cart after clearing cookies | D21: Edge | E21: P3 | F21: Guest has items | G21: — | H21: 1. Clear site cookies 2. Open Cart | I21: Cart is empty (guest cart tied to cookie). | J21: Manual | M21: Not Run
A22: TC-CART-021 | B22: Compatibility | C22: Add to cart on all browsers / mobile | D22: Compatibility | E22: P2 | F22: — | G22: — | H22: 1. Run TC-CART-001 and TC-CART-004 on every project | I22: Same behaviour on Chromium, Firefox, WebKit, Pixel 7, iPhone 14. | J22: Automated | K22: playwright.config.ts (projects) | L22: @smoke | M22: Not Run

Sheet Place Order
A1: TC ID | B1: Scenario | C1: Title | D1: Type | E1: Priority | F1: Preconditions | G1: Test Data | H1: Steps | I1: Expected Result | J1: Automation | K1: Automated In | L1: Tags | M1: Status | N1: Actual Result / Notes
A2: TC-ORDER-001 | B2: E2E (demo) | C2: Logged-in user adds a product and places an order | D2: Functional | E2: P1 | F2: Registered user, empty cart | G2: Samsung galaxy s6; order form: name, country, city, card 4111111111111111, month, year | H2: 1. Log in with valid credentials 2. Open Samsung galaxy s6, note price 3. Add to cart 4. Open Cart; verify line and total 5. Click 'Place Order'; verify modal total 6. Fill form and click 'Purchase' 7. Verify receipt; click OK 8. Re-open Cart | I2: Receipt 'Thank you for your purchase!' with numeric Id, Amount = cart total, Name = entered name, card last 4 digits, today's date; OK returns to home; cart is now empty. | J2: Automated | K2: tests/ui/checkout.spec.ts | L2: @smoke @regression @e2e | M2: Not Run
A3: TC-ORDER-002 | B3: Checkout | C3: Guest orders several products | D3: Functional | E3: P1 | F3: Guest | G3: Nexus 6 + Apple monitor 24 | H3: 1. Add two products as guest 2. Open Cart 3. Place Order with valid data | I3: Receipt Amount = sum of both prices. | J3: Automated | K3: tests/ui/checkout.spec.ts | L3: @regression | M3: Not Run
A4: TC-ORDER-003 | B4: Checkout | C4: Only mandatory fields filled (Name, Credit card) | D4: Edge | E4: P2 | F4: Cart has 1 item | G4: country/city/month/year empty | H4: 1. Open Place Order 2. Fill only Name and Credit card 3. Click 'Purchase' | I4: Order succeeds; receipt shows the entered name. | J4: Automated | K4: tests/ui/checkout.spec.ts | L4: @regression | M4: Not Run
A5: TC-ORDER-004 | B5: Validation | C5: Name empty | D5: Negative | E5: P1 | F5: Cart has 1 item | G5: name='' | H5: 1. Open Place Order 2. Fill everything except Name 3. Click 'Purchase' | I5: Alert 'Please fill out Name and Creditcard.'; no receipt; cart unchanged. | J5: Automated | K5: tests/ui/checkout.spec.ts | L5: @regression | M5: Not Run
A6: TC-ORDER-005 | B6: Validation | C6: Credit card empty | D6: Negative | E6: P1 | F6: Cart has 1 item | G6: card='' | H6: 1. Open Place Order 2. Fill everything except Credit card 3. Click 'Purchase' | I6: Alert 'Please fill out Name and Creditcard.'; no receipt; cart unchanged. | J6: Automated | K6: tests/ui/checkout.spec.ts | L6: @regression | M6: Not Run
A7: TC-ORDER-006 | B7: Validation | C7: All fields empty | D7: Negative | E7: P2 | F7: Cart has 1 item | G7: all empty | H7: 1. Open Place Order 2. Click 'Purchase' without filling anything | I7: Validation alert; no receipt; cart unchanged. | J7: Automated | K7: tests/ui/checkout.spec.ts | L7: @regression | M7: Not Run
A8: TC-ORDER-007 | B8: Validation | C8: Name is whitespace only | D8: Negative | E8: P2 | F8: Cart has 1 item | G8: name=' ' | H8: 1. Open Place Order 2. Enter spaces as Name, valid card 3. Click 'Purchase' | I8: Order is rejected like an empty name. | J8: Automated | K8: tests/ui/checkout.spec.ts | L8: @known-bug | M8: Not Run
A9: TC-ORDER-008 | B9: Validation | C9: Validation message text | D9: UI | E9: P3 | F9: Cart has 1 item | G9: name='' card='' | H9: 1. Open Place Order 2. Click 'Purchase' | I9: Alert text is exactly 'Please fill out Name and Creditcard.' | J9: Automated | K9: tests/ui/checkout.spec.ts | L9: @regression | M9: Not Run
A10: TC-ORDER-009 | B10: Modal behaviour | C10: Closing the order form keeps the cart | D10: Edge | E10: P2 | F10: Cart has 1 item | G10: valid data | H10: 1. Open Place Order 2. Fill the form 3. Click 'Close' 4. Reload Cart | I10: No order placed; cart still has the item. | J10: Automated | K10: tests/ui/checkout.spec.ts | L10: @regression | M10: Not Run
A11: TC-ORDER-010 | B11: Edge input | C11: Unicode / special characters in name | D11: Edge | E11: P3 | F11: Cart has 1 item | G11: Nguyễn Văn Ánh <b>&"' | H11: 1. Place an order with the special-character name | I11: Receipt shows the name exactly as typed; no HTML is rendered/executed. | J11: Automated | K11: tests/ui/checkout.spec.ts | L11: @regression | M11: Not Run
A12: TC-ORDER-011 | B12: Receipt | C12: Receipt date shows the current month | D12: Functional | E12: P2 | F12: Cart has 1 item | G12: — | H12: 1. Place an order 2. Read 'Date' on the receipt | I12: Date = today's day/month/year. | J12: Automated | K12: tests/ui/checkout.spec.ts | L12: @known-bug | M12: Not Run
A13: TC-ORDER-012 | B13: Negative | C13: Order with an empty cart | D13: Negative | E13: P1 | F13: Empty cart | G13: valid form data | H13: 1. Open empty Cart 2. Click 'Place Order' 3. Fill valid data, click 'Purchase' | I13: Order is blocked (nothing to buy). | J13: Automated | K13: tests/ui/checkout.spec.ts | L13: @known-bug | M13: Not Run
... A15: TC-ORDER-014 | B15: Security | C15: Receipt masks the card number | D15: Security | E15: P2 | F15: Cart has 1 item | G15: card 4111111111111111 | H15: 1. Place an order 2. Inspect 'Card Number' on the receipt | I15: Only the last 4 digits are shown (e.g. **** 1111). | J15: Automated | K15: tests/ui/checkout.spec.ts | L15: @known-bug | M15: Not Run
A16: TC-ORDER-015 | B16: Validation | C16: Invalid month / year values | D16: Negative | E16: P3 | F16: Cart has 1 item | G16: month=13, year=1999 | H16: 1. Enter invalid month and a past year 2. Click 'Purchase' | I16: Validation error for expiry date. | J16: Candidate | M16: Not Run
A17: TC-ORDER-016 | B17: Robustness | C17: Double-click 'Purchase' | D17: Edge | E17: P3 | F17: Cart has 1 item | G17: valid data | H17: 1. Fill valid data 2. Double-click 'Purchase' | I17: Only one order/receipt is created. | J17: Manual | M17: Not Run
A18: TC-ORDER-017 | B18: Edge input | C18: Very long input values | D18: Edge | E18: P3 | F18: Cart has 1 item | G18: 300-char name, 50-digit card | H18: 1. Fill the form with very long values 2. Click 'Purchase' | I18: Handled gracefully: validation or truncation, receipt layout not broken. | J18: Candidate | M18: Not Run

Sheet API & Performance
A1: TC ID | B1: Scenario | C1: Title | D1: Type | E1: Priority | F1: Preconditions | G1: Test Data | H1: Steps | I1: Expected Result | J1: Automation | K1: Automated In | L1: Tags | M1: Status | N1: Actual Result / Notes
A2: TC-API-001 | B2: Auth API | C2: Sign up then log in returns an auth token | D2: Functional | E2: P1 | F2: — | G2: new unique user | H2: 1. POST /signup 2. POST /login | I2: Signup has no errorMessage; login returns 'Auth_token: <token>'. | J2: Automated | K2: tests/api/auth.api.spec.ts | L2: @api @smoke | M2: Not Run
A3: TC-API-002 | B3: Auth API | C3: Duplicate sign-up is rejected | D3: Negative | E3: P2 | F3: A registered user exists (auto-provisioned via API by the framework) | G3: existing username | H3: 1. POST /signup with an existing username | I3: errorMessage 'This user already exist.' | J3: Automated | K3: tests/api/auth.api.spec.ts | L3: @api | M3: Not Run
A4: TC-API-003 | B4: Auth API | C4: Wrong password | D4: Negative | E4: P1 | F4: A registered user exists (auto-provisioned via API by the framework) | G4: wrong password | H4: 1. POST /login with wrong password | I4: errorMessage 'Wrong password.' | J4: Automated | K4: tests/api/auth.api.spec.ts | L4: @api | M4: Not Run
A5: TC-API-004 | B5: Auth API | C5: Unknown user | D5: Negative | E5: P2 | F5: — | G5: random username | H5: 1. POST /login | I5: errorMessage 'User does not exist.' | J5: Automated | K5: tests/api/auth.api.spec.ts | L5: @api | M5: Not Run
A6: TC-API-005 | B6: Catalog API | C6: /entries contract | D6: Functional | E6: P1 | F6: — | G6: — | H6: 1. GET /entries | I6: 200; Items[] non-empty; each has id, title, price>0, cat∈{phone,notebook,monitor}, desc, img. | J6: Automated | K6: tests/api/catalog-cart.api.spec.ts | L6: @api @smoke | M6: Not Run
A7: TC-API-006 | B7: Catalog API | C7: /view returns the requested product | D7: Functional | E7: P2 | F7: — | G7: id=1 | H7: 1. POST /view {id:1} | I7: Title 'Samsung galaxy s6' and valid contract. | J7: Automated | K7: tests/api/catalog-cart.api.spec.ts | L7: @api | M7: Not Run
A8: TC-API-007 | B8: Catalog API | C8: /bycat filters by category | D8: Functional | E8: P2 | F8: — | G8: cat=phone | H8: 1. POST /bycat {cat:'phone'} | I8: All items have cat='phone'. | J8: Automated | K8: tests/api/catalog-cart.api.spec.ts | L8: @api | M8: Not Run
A9: TC-API-008 | B9: Cart API | C9: Add, view and delete a cart line | D9: Functional | E9: P1 | F9: Logged-in token, empty cart | G9: Nexus 6 | H9: 1. POST /addtocart 2. POST /viewcart 3. POST /deleteitem 4. POST /viewcart | I9: Line present after add, gone after delete. | J9: Automated | K9: tests/api/catalog-cart.api.spec.ts | L9: @api @smoke | M9: Not Run
A10: TC-API-009 | B10: Cart API | C10: Each add creates a separate line | D10: Edge | E10: P2 | F10: Logged-in token, empty cart | G10: Nexus 6 ×2 | H10: 1. POST /addtocart twice 2. POST /viewcart | I10: 2 lines with distinct ids. | J10: Automated | K10: tests/api/catalog-cart.api.spec.ts | L10: @api | M10: Not Run
A11: TC-PERF-001 | B11: Performance | C11: Home page load budget | D11: Performance | E11: P2 | F11: — | G11: budget PERF_PAGE_LOAD_MS / PERF_PRODUCTS_RENDERED_MS | H11: 1. Navigate to home 2. Collect Navigation Timing + time to product grid | I11: load < 5s; grid visible < 6s (configurable). Metrics attached to the report. | J11: Automated | K11: tests/perf/performance.perf.spec.ts | L11: @perf | M11: Not Run
A12: TC-PERF-002 | B12: Performance | C12: /entries latency p50 | D12: Performance | E12: P2 | F12: — | G12: 5 calls | H12: 1. Call GET /entries 5 times | I12: p50 < 2s (configurable). | J12: Automated | K12: tests/perf/performance.perf.spec.ts | L12: @perf | M12: Not Run
A13: TC-PERF-003 | B13: Performance | C13: /login latency | D13: Performance | E13: P3 | F13: A registered user exists (auto-provisioned via API by the framework) | G13: — | H13: 1. POST /login | I13: Response < 2s (configurable). | J13: Automated | K13: tests/perf/performance.perf.spec.ts | L13: @perf | M13: Not Run
A14: TC-PERF-004 | B14: Load | C14: Catalogue API under concurrent load (k6) | D14: Performance | E14: P3 | F14: k6 installed | G14: 5–20 virtual users, ~1 min | H14: 1. k6 run perf/k6/catalog-load.js | I14: Error rate < 1%; p95 < 2s. | J14: Automated | K14: perf/k6/catalog-load.js | L14: k6 | M14: Not Run

Sheet Concurrency & Contract
A1: TC ID | B1: Scenario | C1: Title | D1: Type | E1: Priority | F1: Preconditions | G1: Test Data | H1: Steps | I1: Expected Result | J1: Automation | K1: Automated In | L1: Tags | M1: Status | N1: Actual Result / Notes
A2: TC-CONC-001 | B2: Concurrency | C2: Parallel add-to-cart requests are all persisted, none lost | D2: Functional | E2: P1 | F2: Registered user, empty cart (auto-provisioned via API by the framework) | G2: 10 parallel POST /addtocart, unique line ids, Nexus 6 | H2: 1. Send 10 POST /addtocart in parallel, each with its own line id 2. POST /viewcart | I2: All 10 requests return 200; cart has exactly 10 lines and their ids equal the ids sent (no lost writes). | J2: Automated | K2: tests/api/concurrency.api.spec.ts | L2: @api @concurrency @regression | M2: Not Run
A3: TC-CONC-002 | B3: Idempotency | C3: Replaying the same request in parallel creates exactly one line | D3: Edge | E3: P1 | F3: Registered user, empty cart (auto-provisioned via API by the framework) | G3: 10 identical POST /addtocart with the same line id | H3: 1. Send the same POST /addtocart (same id, same payload) 10 times in parallel 2. POST /viewcart | I3: All requests return 200; cart has exactly 1 line with that id and product (replay is idempotent). | J3: Automated | K3: tests/api/concurrency.api.spec.ts | L3: @api @concurrency @idempotency @smoke | M3: Not Run
A4: TC-CONC-003 | B4: Idempotency | C4: Parallel deletes of the same line are safe | D4: Edge | E4: P2 | F4: Registered user, empty cart (auto-provisioned via API by the framework); cart has 1 line | G4: 5 parallel POST /deleteitem with the same id | H4: 1. Add 1 line 2. Send 5 POST /deleteitem for that line in parallel 3. POST /viewcart | I4: No request errors; cart is empty; no exception from deleting an already-deleted line. | J4: Automated | K4: tests/api/concurrency.api.spec.ts | L4: @api @concurrency @idempotency | M4: Not Run
A5: TC-CONC-004 | B5: Idempotency | C5: Placing the order twice in parallel empties the cart once without errors | D5: Edge | E5: P1 | F5: Registered user, empty cart (auto-provisioned via API by the framework); cart has 2 lines | G5: 2 parallel POST /deletecart (place order) | H5: 1. Add 2 products 2. Send 2 place-order requests in parallel 3. POST /viewcart | I5: Both return 200; cart ends empty; no partial or duplicated state. | J5: Automated | K5: tests/api/concurrency.api.spec.ts | L5: @api @concurrency @idempotency | M5: Not Run
A6: TC-CONC-005 | B6: Idempotency | C6: Reusing an idempotency key with a different payload is rejected | D6: Negative | E6: P1 | F6: Registered user, empty cart (auto-provisioned via API by the framework) | G6: Same line id: first Samsung galaxy s6, then Apple monitor 24 | H6: 1. POST /addtocart id=X prod_id=1 2. POST /addtocart id=X prod_id=10 3. POST /viewcart | I6: Second request rejected (409/422) or ignored; cart keeps the original line with prod_id=1. | J6: Automated | K6: tests/api/concurrency.api.spec.ts | L6: @api @concurrency @known-bug | M6: Not Run | N6: Known defect BUG-07: the line is silently overwritten with prod_id=10.
A7: TC-CONC-006 | B7: Concurrency | C7: Same user adding from two tabs at once keeps both items | D7: Functional | E7: P2 | F7: User logged in, two tabs in one session | G7: Tab 1: Nexus 6, Tab 2: Sony vaio i5 | H7: 1. Open a different product in each tab 2. Click 'Add to cart' in both tabs at the same time 3. Check the cart | I7: Cart contains both products exactly once. | J7: Automated | K7: tests/ui/concurrency.spec.ts | L7: @concurrency @regression | M7: Not Run
A8: TC-CONC-007 | B8: Double submit | C8: Double-clicking 'Add to cart' adds the product once | D8: Edge | E8: P1 | F8: User logged in, empty cart | G8: Nexus 6 | H8: 1. Open the product page 2. Double-click 'Add to cart' 3. Wait for requests to settle; check the cart | I8: Button is disabled / debounced after the first click; cart has 1 line. | J8: Automated | K8: tests/ui/concurrency.spec.ts | L8: @concurrency @known-bug | M8: Not Run | N8: Known defect BUG-08: two /addtocart requests are sent and 2 lines are created.
A9: TC-CONC-008 | B9: Double submit | C9: Double-clicking 'Purchase' submits the order once | D9: Edge | E9: P1 | F9: User logged in, cart has 1 item | G9: Valid order form | H9: 1. Open Place Order and fill the form 2. Double-click 'Purchase' 3. Count place-order requests | I9: Exactly one order request is sent (payment-style double-charge protection). | J9: Automated | K9: tests/ui/concurrency.spec.ts | L9: @concurrency @known-bug | M9: Not Run | N9: Known defect BUG-09: two /deletecart requests are sent; on a real gateway this is a double charge.
A10: TC-CTR-001 | B10: Contract /login | C10: Successful login returns an Auth_token string | D10: Functional | E10: P1 | F10: Registered user, empty cart (auto-provisioned via API by the framework) | G10: valid username / password | H10: 1. POST /login with valid credentials 2. Validate the body against loginSuccessSchema | I10: HTTP 200, content-type application/json, body is a JSON string matching ^Auth_token: \S+$. | J10: Automated | K10: tests/api/contract.api.spec.ts | L10: @api @contract @smoke | M10: Not Run
A11: TC-CTR-002 | B11: Contract /login | C11: Failed login returns the error contract | D11: Negative | E11: P1 | F11: Registered user, empty cart (auto-provisioned via API by the framework) | G11: wrong password; unknown username | H11: 1. POST /login with a wrong password 2. POST /login with an unknown user 3. Validate each body against errorSchema | I11: Body is exactly { errorMessage: string } with 'Wrong password.' / 'User does not exist.'. | J11: Automated | K11: tests/api/contract.api.spec.ts | L11: @api @contract @regression | M11: Not Run
A12: TC-CTR-003 | B12: Contract cart | C12: /addtocart succeeds with an empty body and /viewcart returns the typed line | D12: Functional | E12: P1 | F12: Registered user, empty cart (auto-provisioned via API by the framework) | G12: Nexus 6, fixed line id | H12: 1. POST /addtocart 2. POST /viewcart 3. Validate against viewCartSchema | I12: /addtocart: 200 with empty body. /viewcart: { Items: [{ cookie: string, id: string, prod_id: integer }] } with no extra fields. | J12: Automated | K12: tests/api/contract.api.spec.ts | L12: @api @contract @smoke | M12: Not Run
A13: TC-CTR-004 | B13: Contract cart | C13: /viewcart of an empty cart returns an empty Items array | D13: Edge | E13: P2 | F13: Registered user, empty cart (auto-provisioned via API by the framework) | G13: — | H13: 1. POST /viewcart for an empty cart | I13: Body matches viewCartSchema and Items is []. | J13: Automated | K13: tests/api/contract.api.spec.ts | L13: @api @contract @regression | M13: Not Run
A14: TC-CTR-005 | B14: Contract cart | C14: Malformed token returns the error contract on /addtocart and /viewcart | D14: Negative | E14: P2 | F14: — | G14: cookie='not-a-token' | H14: 1. POST /addtocart with a malformed token 2. POST /viewcart with a malformed token | I14: Body matches errorSchema with 'Bad parameter, token malformed.'; nothing is stored. | J14: Automated | K14: tests/api/contract.api.spec.ts | L14: @api @contract @regression | M14: Not Run
A15: TC-CTR-006 | B15: Contract errors | C15: Errors are reported with a 4xx status code | D15: Negative | E15: P2 | F15: — | G15: unknown username | H15: 1. POST /login with an unknown user 2. Check the HTTP status | I15: HTTP status is 4xx (e.g. 401/404), not 200. | J15: Automated | K15: tests/api/contract.api.spec.ts | L15: @api @contract @known-bug | M15: Not Run | N15: Known defect BUG-10: every error is HTTP 200 with an errorMessage body.
A16: TC-CTR-007 | B16: Contract cart | C16: /addtocart rejects a product id that does not exist | D16: Negative | E16: P2 | F16: Registered user, empty cart (auto-provisioned via API by the framework) | G16: prod_id=999999 | H16: 1. POST /addtocart with prod_id=999999 2. POST /viewcart | I16: Request rejected (4xx); cart stays empty. | J16: Automated | K16: tests/api/contract.api.spec.ts | L16: @api @contract @known-bug | M16: Not Run | N16: Known defect BUG-11: the line is stored with prod_id=999999.
A17: TC-K6-001 | B17: Load (k6) | C17: Checkout flow smoke: 1 VU for 30 s | D17: Performance | E17: P2 | F17: k6 installed; 1 user signed up in setup() | G17: SCENARIO=smoke | H17: 1. npm run perf:smoke 2. Flow per iteration: login → add to cart → verify cart → place order → verify cart emptied | I17: All thresholds pass: http_req_failed <1%, p95 <2 s, p99 <4 s, per-step p95 <1.5 s, checks >99%, business_errors <1%, checkout p95 <6 s. | J17: Automated | K17: perf/k6/checkout-flow.js | L17: @perf @k6 @smoke | M17: Not Run | N17: Run 13 Oct 2026: 11 iterations, 100% checks, p95 547 ms — all thresholds passed.
A18: TC-K6-002 | B18: Load (k6) | C18: Checkout flow load: ramp to 5 VUs, hold 1 min | D18: Performance | E18: P2 | F18: k6 installed; PEAK_VUS users signed up in setup() | G18: SCENARIO=load | H18: 1. npm run perf:checkout 2. Same flow as TC-K6-001 | I18: Same thresholds as TC-K6-001 under sustained load. | J18: Automated | K18: perf/k6/checkout-flow.js | L18: @perf @k6 @regression | M18: Not Run | N18: Run nightly / on demand in the CI 'load' job.
A19: TC-K6-003 | B19: Spike (k6) | C19: Checkout flow spike: 1 → 20 VUs in 10 s, hold 30 s, recover | D19: Performance | E19: P1 | F19: k6 installed; 20 users signed up in setup() | G19: SCENARIO=spike PEAK_VUS=20 | H19: 1. npm run perf:spike 2. Watch latency and errors during the ramp and after recovery | I19: Same thresholds as TC-K6-001 during and after the spike; latency returns to baseline after ramp-down. | J19: Automated | K19: perf/k6/checkout-flow.js | L19: @perf @k6 @spike | M19: Not Run | N19: Run 13 Oct 2026: 301 orders, checks 99.90%, p95 557 ms, p99 999 ms, http_req_failed 0.06% (1/1525) — all thresholds passed.

Sheet Test Strategy – Payment Gateway
A1: ID | B1: Area | C1: Risk addressed | D1: Scenario | E1: Type | F1: Priority | G1: Setup / Preconditions | H1: Steps | I1: Expected Result | J1: Test Level | K1: Tooling | L1: DemoBlaze analogue | M1: Status
A2: PG-PAY-01 | B2: Payment & idempotency | C2: Double charge on client retry | D2: Same Idempotency-Key sent twice returns the original result and charges once | E2: Edge | F2: P1 | G2: Merchant account; card token | H2: 1. POST /payments with Idempotency-Key K 2. Repeat the identical request sequentially and 50x in parallel | I2: One charge in the ledger; every response has the same payment_id and status; replays flagged as replay. | J2: API | K2: Playwright API, k6 | L2: TC-CONC-002 | M2: Proposed
A3: PG-PAY-02 | B3: Payment & idempotency | C3: Key reused for a different payment | D3: Same Idempotency-Key with a different amount or card is rejected | E3: Negative | F3: P1 | G3: Payment created with key K | H3: 1. POST /payments with key K and a different amount | I3: 409/422 with a clear error; original payment untouched; no second charge. | J3: API | K3: Playwright API | L3: TC-CONC-005 | M3: Proposed
A4: PG-PAY-03 | B4: Payment & idempotency | C4: Idempotency window | D4: After the key TTL (e.g. 24 h) the same key is treated as a new request | E4: Edge | F4: P2 | G4: Key K older than TTL (time-travel / short TTL in test env) | H4: 1. Replay key K after TTL expiry | I4: Behaviour matches the documented policy (new payment or explicit 'key expired' error); no silent duplicate. | J4: Integration | K4: Testcontainers Redis | L4: — | M4: Proposed
A5: PG-PAY-04 | B5: Payment & idempotency | C5: Illegal state transitions | D5: Payment state machine only allows valid transitions | E5: Negative | F5: P1 | G5: Payments in each state | H5: 1. Try every transition, e.g. CAPTURED→PENDING, REFUNDED→CAPTURED, VOIDED→CAPTURED | I5: Only PENDING→AUTHORIZED→CAPTURED→(PARTIALLY_)REFUNDED and AUTHORIZED→VOIDED succeed; others return 409 and change nothing. | J5: Unit / API | K5: Jest, Playwright API | L5: — | M5: Proposed
A6: PG-PAY-05 | B6: Payment & idempotency | C6: Acquirer timeout leaves money in limbo | D6: Acquirer times out after debiting; client retries | E6: Edge | F6: P1 | G6: WireMock acquirer delays 35 s then returns success | H6: 1. Create payment 2. Client times out and retries with the same key 3. Run status inquiry / reconciliation | I6: Payment stays PENDING, then resolves to the acquirer's real result; customer charged once. | J6: Integration | K6: WireMock, Testcontainers | L6: — | M6: Proposed
A7: PG-PAY-06 | B7: Payment & idempotency | C7: Duplicate / out-of-order webhooks | D7: Webhook delivered twice and out of order | E7: Edge | F7: P1 | G7: Payment AUTHORIZED | H7: 1. Deliver CAPTURED webhook twice 2. Deliver AUTHORIZED after CAPTURED | I7: Processed once (dedupe on event id); final state CAPTURED; merchant notified once. | J7: Integration | K7: WireMock, Kafka | L7: — | M7: Proposed
A8: PG-PAY-07 | B8: Payment & idempotency | C8: Forged webhook | D8: Webhook with missing or invalid HMAC signature | E8: Security | F8: P1 | G8: Webhook secret configured | H8: 1. POST webhook without signature 2. POST with a wrong signature 3. POST with an old timestamp | I8: 401/400; no state change; security event logged. | J8: API | K8: Playwright API | L8: — | M8: Proposed
A9: PG-PAY-08 | B9: Payment & idempotency | C9: Over-refund | D9: Refunds cannot exceed the captured amount | E9: Negative | F9: P1 | G9: Payment captured 100,000 VND | H9: 1. Refund 60,000 2. Refund 50,000 3. Refund 40,000 | I9: Second refund rejected; total refunded ≤ captured; balances consistent. | J9: API | K9: Playwright API | L9: — | M9: Proposed
A10: PG-PAY-09 | B10: Payment & idempotency | C10: Rounding / currency errors | D10: Amounts in minor units with correct currency rules | E10: Edge | F10: P1 | G10: VND (0 decimals), USD (2), KWD (3) | H10: 1. Pay 0.1 + 0.2 USD 2. Pay 1 VND 3. Pay with the max amount | I10: Stored as integer minor units / DECIMAL; no float drift; currency exponent respected. | J10: Unit / API | K10: Jest, Playwright API | L10: — | M10: Proposed
A11: PG-PAY-10 | B11: Payment & idempotency | C11: Ledger ≠ settlement | D11: Daily reconciliation with the acquirer settlement file | E11: Functional | F11: P1 | G11: Settlement file with a missing, an extra and an amount-mismatch row | H11: 1. Run the reconciliation job | I11: All 3 mismatches flagged with reason; matched rows marked SETTLED; report produced. | J11: Batch / Integration | K11: Testcontainers, S3 (LocalStack) | L11: — | M11: Proposed
A12: PG-CONC-01 | B12: Concurrency | C12: Overdraft via race condition | D12: Two concurrent debits when the balance covers only one | E12: Edge | F12: P1 | G12: Wallet balance 100 | H12: 1. Send two 80 debits at the same time (50 repetitions) | I12: Exactly one succeeds each time; balance never negative. | J12: API / Load | K12: k6, Promise.all | L12: TC-CONC-001 | M12: Proposed
... A63: PG-PERF-04 | B63: Performance | C63: Unknown limits | D63: Stress to breaking point | E63: Performance | F63: P2 | G63: Isolated environment | H63: 1. Increase TPS stepwise until SLA breach | I63: Max sustainable TPS and the first bottleneck documented; graceful failure (429/503, not crashes). | J63: Load | K63: k6 | L63: — | M63: Proposed

Sheet Defects & Observations
A1: ID | B1: Area | C1: Summary | D1: Severity | E1: Steps to Reproduce | F1: Expected | G1: Actual | H1: Covered by | I1: Evidence / Status
A2: BUG-01 | B2: Place Order | C2: Receipt date shows the wrong month (zero-based) | D2: Medium | E2: Place any order and read 'Date' on the receipt | F2: Date shows today's month | G2: Month is one less (JS getMonth() is zero-based); e.g. October shows as 9 | H2: TC-ORDER-011 | I2: Verified live on demoblaze.com (13 Oct 2026): receipt showed 13/9/2026 in October
A3: BUG-02 | B3: Place Order | C3: An order can be placed with an empty cart | D3: High | E3: Open an empty cart → Place Order → fill name + card → Purchase | F3: Purchase blocked | G3: Receipt is shown with Amount 0 | H3: TC-ORDER-012 | I3: Verified live on demoblaze.com (13 Oct 2026): receipt with Amount 0 USD
A4: BUG-03 | B4: Place Order | C4: No format validation on credit card | D4: Medium | E4: Enter 'not-a-card' as card → Purchase | F4: Validation error | G4: Order accepted | H4: TC-ORDER-013 | I4: Verified live on demoblaze.com (13 Oct 2026): card 'not-a-card' accepted
A5: BUG-04 | B5: Place Order | C5: Whitespace-only name passes validation | D5: Low | E5: Enter ' ' as name → Purchase | F5: Treated as empty | G5: Order accepted | H5: TC-ORDER-007 | I5: Verified live on demoblaze.com (13 Oct 2026): receipt shows empty 'Name:'
A6: BUG-05 | B6: Place Order / Security | C6: Full card number echoed on the receipt | D6: Medium | E6: Place an order; read 'Card Number' | F6: Masked (last 4 digits) | G6: Full number displayed | H6: TC-ORDER-014 | I6: Verified live on demoblaze.com (13 Oct 2026): full 16-digit number shown
A7: BUG-06 | B7: Cart | C7: Inconsistent alert text for add to cart | D7: Low | E7: Add a product as guest vs. logged-in user | F7: Same message | G7: Guest: 'Product added' / user: 'Product added.' | H7: TC-CART-001 / 004 | I7: Logged-in alert 'Product added.' verified live; guest variant from prod.js
A8: BUG-07 | B8: Cart API / Idempotency | C8: Reused cart line id silently overwrites the existing line | D8: High | E8: POST /addtocart id=X prod_id=1, then POST /addtocart id=X prod_id=10; POST /viewcart | F8: Second request rejected as a conflicting idempotency key (409/422); original line kept | G8: Line X now has prod_id=10; no error returned | H8: TC-CONC-005 | I8: Verified live via API (13 Oct 2026)
A9: BUG-08 | B9: Cart / Double submit | C9: Double-clicking 'Add to cart' adds the product twice | D9: Medium | E9: Log in → open a product → double-click 'Add to cart' → open Cart | F9: Button debounced; one line in the cart | G9: Two /addtocart requests; 2 identical lines | H9: TC-CONC-007 | I9: Verified live on Chromium, Firefox and WebKit (13 Oct 2026)
A10: BUG-09 | B10: Place Order / Double submit | C10: Double-clicking 'Purchase' submits the order twice | D10: High | E10: Cart with 1 item → Place Order → fill form → double-click 'Purchase' | F10: One order request; button disabled after first click | G10: Two /deletecart (order) requests sent — on a real gateway this is a double charge | H10: TC-CONC-008 | I10: Verified live on Chromium, Firefox and WebKit (13 Oct 2026)
A11: BUG-10 | B11: API / Contract | C11: Errors returned with HTTP 200 | D11: Medium | E11: POST /login with an unknown user; POST /viewcart with a malformed token | F11: 4xx status (401/404/400) with an error body | G11: HTTP 200 with { errorMessage } — clients and monitors cannot detect failures by status | H11: TC-CTR-006 | I11: Verified live via API (13 Oct 2026)
A12: BUG-11 | B12: Cart API / Validation | C12: Non-existent product id accepted by /addtocart | D12: Medium | E12: POST /addtocart with prod_id=999999; POST /viewcart | F12: Request rejected; cart unchanged | G12: Line stored with prod_id=999999 | H12: TC-CTR-007 | I12: Verified live via API (13 Oct 2026)
A13: OBS-01 | B13: Login / Security | C13: Password only base64-encoded client-side | D13: Info | E13: Inspect POST /login payload | F13: Password protected by TLS only; no reversible encoding implying security | G13: Base64 of the password sent (reversible); acceptable over HTTPS but misleading | H13: TC-LOGIN-023 (related) | I13: Observation, not a functional defect
